tests/__init__.py
tests/integration/__init__.py
tests/integration/providers/__init__.py
tests/integration/providers/test_twindb_aws.py
tests/unit/__init__.py
tests/unit/test_tagset.py
tests/unit/test_twindb_chef.py
tests/unit/test_twindb_galera.py
tests/unit/test_twindb_infrastructure.py
tests/unit/test_util.py
tests/unit/check_http/__init__.py
tests/unit/check_http/check_http_response/__init__.py
tests/unit/check_http/check_http_response/test_str.py
tests/unit/check_http/check_response/__init__.py
tests/unit/check_http/check_response/test_str.py
tests/unit/check_http/http_checker/__init__.py
tests/unit/check_http/http_checker/test_check.py
tests/unit/config/__init__.py
tests/unit/config/test_config.py
tests/unit/loader/__init__.py
tests/unit/loader/test_loader.py
tests/unit/providers/__init__.py
tests/unit/providers/test_twindb_aws.py
tests/unit/providers/aws/__init__.py
tests/unit/providers/aws/test_launch_ec2_instance.py
twindb_infrastructure/__init__.py
twindb_infrastructure/check_http.py
twindb_infrastructure/cli.py
twindb_infrastructure/loader.py
twindb_infrastructure/monitoring.py
twindb_infrastructure/switchover.py
twindb_infrastructure/tagset.py
twindb_infrastructure/twindb_aws.py
twindb_infrastructure/twindb_chef.py
twindb_infrastructure/twindb_galera.py
twindb_infrastructure/util.py
twindb_infrastructure/config/__init__.py
twindb_infrastructure/config/aws_credentials.py
twindb_infrastructure/config/cloudflare_credentials.py
twindb_infrastructure/config/config.py
twindb_infrastructure/config/credentials.py
twindb_infrastructure/config/ssh_credentials.py
twindb_infrastructure/providers/__init__.py
twindb_infrastructure/providers/aws.py
twindb_infrastructure/providers/cloudflare.py
twindb_infrastructure/providers/common.py
twindb_infrastructure-1.4.2.dist-info/AUTHORS.rst
twindb_infrastructure-1.4.2.dist-info/METADATA
twindb_infrastructure-1.4.2.dist-info/WHEEL
twindb_infrastructure-1.4.2.dist-info/entry_points.txt
twindb_infrastructure-1.4.2.dist-info/top_level.txt
twindb_infrastructure-1.4.2.dist-info/RECORD
