Metadata-Version: 2.1
Name: twindb-infrastructure
Version: 1.4.2
Summary: TwinDB Infrastructure is a collection of everything to manage TwinDB infrastructure
Home-page: https://github.com/twindb/twindb_infrastructure
Author: TwinDB Development Team
Author-email: dev@twindb.com
License: Apache Software License 2.0
Keywords: twindb_infrastructure
Platform: UNKNOWN
Classifier: Development Status :: 2 - Pre-Alpha
Classifier: Intended Audience :: Developers
Classifier: Natural Language :: English
Classifier: Programming Language :: Python :: 2
Classifier: Programming Language :: Python :: 2.6
Classifier: Programming Language :: Python :: 2.7
Requires-Dist: boto3 (~=1.9)
Requires-Dist: Click (~=7.0)
Requires-Dist: logutils (~=0.3)
Requires-Dist: pymysql (~=0.9)
Requires-Dist: requests (~=2.22)
Requires-Dist: urllib3 (<1.25,>=1.20)
